[
    {
        "editted_at": 1608628792783,
        "editted_at_": 1608628792783,
        "sample_name": "40",
        "operation_type": "initialize",
        "x": null,
        "y": null,
        "color": null,
        "force": null,
        "editted_by": "kondo"
    },
    {
        "editted_at": 1608628793043,
        "editted_at_": 1608628793039.284,
        "sample_name": "40",
        "operation_type": "start",
        "x": null,
        "y": null,
        "color": null,
        "force": null,
        "editted_by": "kondo"
    },
    {
        "editted_at": 1608628793835,
        "editted_at_": 1608628793835.124,
        "sample_name": "40",
        "operation_type": "start_drawing",
        "x": 313,
        "y": 341.5,
        "color": "#0F0",
        "force": 0.240234375,
        "editted_by": "kondo"
    },
    {
        "editted_at": 1608628793842,
        "editted_at_": 1608628793836.009,
        "sample_name": "40",
        "operation_type": "draw_line",
        "x": 312.5,
        "y": 341.5,
        "color": "#0F0",
        "force": 0.2666015625,
        "editted_by": "kondo"
    },
    {
        "editted_at": 1608628793859,
        "editted_at_": 1608628793849.969,
        "sample_name": "40",
        "operation_type": "draw_line",
        "x": 311.5,
        "y": 341,
        "color": "#0F0",
        "force": 0.2666015625,
        "editted_by": "kondo"
    },
    {
        "editted_at": 1608628793876,
        "editted_at_": 1608628793871.469,
        "sample_name": "40",
        "operation_type": "draw_line",
        "x": 311,
        "y": 340.5,
        "color": "#0F0",
        "force": 0.2705078125,
        "editted_by": "kondo"
    },
    {
        "editted_at": 1608628793893,
        "editted_at_": 1608628793887.5388,
        "sample_name": "40",
        "operation_type": "draw_line",
        "x": 310,
        "y": 340.5,
        "color": "#0F0",
        "force": 0.28125,
        "editted_by": "kondo"
    },
    {
        "editted_at": 1608628793910,
        "editted_at_": 1608628793902.984,
        "sample_name": "40",
        "operation_type": "draw_line",
        "x": 309.5,
        "y": 339.5,
        "color": "#0F0",
        "force": 0.3046875,
        "editted_by": "kondo"
    },
    {
        "editted_at": 1608628793926,
        "editted_at_": 1608628793918.124,
        "sample_name": "40",
        "operation_type": "draw_line",
        "x": 308.5,
        "y": 338.5,
        "color": "#0F0",
        "force": 0.3291015625,
        "editted_by": "kondo"
    },
    {
        "editted_at": 1608628793943,
        "editted_at_": 1608628793942.084,
        "sample_name": "40",
        "operation_type": "draw_line",
        "x": 308.5,
        "y": 335.5,
        "color": "#0F0",
        "force": 0.3681640625,
        "editted_by": "kondo"
    },
    {
        "editted_at": 1608628793960,
        "editted_at_": 1608628793956.919,
        "sample_name": "40",
        "operation_type": "draw_line",
        "x": 308.5,
        "y": 334,
        "color": "#0F0",
        "force": 0.390625,
        "editted_by": "kondo"
    },
    {
        "editted_at": 1608628793977,
        "editted_at_": 1608628793971.719,
        "sample_name": "40",
        "operation_type": "draw_line",
        "x": 308,
        "y": 332,
        "color": "#0F0",
        "force": 0.41796875,
        "editted_by": "kondo"
    },
    {
        "editted_at": 1608628793993,
        "editted_at_": 1608628793986.534,
        "sample_name": "40",
        "operation_type": "draw_line",
        "x": 307.5,
        "y": 330,
        "color": "#0F0",
        "force": 0.451171875,
        "editted_by": "kondo"
    },
    {
        "editted_at": 1608628794010,
        "editted_at_": 1608628794008.129,
        "sample_name": "40",
        "operation_type": "draw_line",
        "x": 306.5,
        "y": 326.5,
        "color": "#0F0",
        "force": 0.4853515625,
        "editted_by": "kondo"
    },
    {
        "editted_at": 1608628794027,
        "editted_at_": 1608628794023.9038,
        "sample_name": "40",
        "operation_type": "draw_line",
        "x": 306,
        "y": 323.5,
        "color": "#0F0",
        "force": 0.49609375,
        "editted_by": "kondo"
    },
    {
        "editted_at": 1608628794043,
        "editted_at_": 1608628794038.324,
        "sample_name": "40",
        "operation_type": "draw_line",
        "x": 305.5,
        "y": 320.5,
        "color": "#0F0",
        "force": 0.5009765625,
        "editted_by": "kondo"
    },
    {
        "editted_at": 1608628794060,
        "editted_at_": 1608628794053.0989,
        "sample_name": "40",
        "operation_type": "draw_line",
        "x": 305,
        "y": 318,
        "color": "#0F0",
        "force": 0.5126953125,
        "editted_by": "kondo"
    },
    {
        "editted_at": 1608628794077,
        "editted_at_": 1608628794068.729,
        "sample_name": "40",
        "operation_type": "draw_line",
        "x": 304,
        "y": 316,
        "color": "#0F0",
        "force": 0.529296875,
        "editted_by": "kondo"
    },
    {
        "editted_at": 1608628794093,
        "editted_at_": 1608628794091.9539,
        "sample_name": "40",
        "operation_type": "draw_line",
        "x": 302.5,
        "y": 312.5,
        "color": "#0F0",
        "force": 0.544921875,
        "editted_by": "kondo"
    },
    {
        "editted_at": 1608628794110,
        "editted_at_": 1608628794107.149,
        "sample_name": "40",
        "operation_type": "draw_line",
        "x": 302,
        "y": 310,
        "color": "#0F0",
        "force": 0.548828125,
        "editted_by": "kondo"
    },
    {
        "editted_at": 1608628794127,
        "editted_at_": 1608628794121.649,
        "sample_name": "40",
        "operation_type": "draw_line",
        "x": 302,
        "y": 307.5,
        "color": "#0F0",
        "force": 0.5546875,
        "editted_by": "kondo"
    },
    {
        "editted_at": 1608628794143,
        "editted_at_": 1608628794136.429,
        "sample_name": "40",
        "operation_type": "draw_line",
        "x": 301.5,
        "y": 305,
        "color": "#0F0",
        "force": 0.5458984375,
        "editted_by": "kondo"
    },
    {
        "editted_at": 1608628794160,
        "editted_at_": 1608628794158.5789,
        "sample_name": "40",
        "operation_type": "draw_line",
        "x": 300.5,
        "y": 301,
        "color": "#0F0",
        "force": 0.564453125,
        "editted_by": "kondo"
    },
    {
        "editted_at": 1608628794177,
        "editted_at_": 1608628794173.604,
        "sample_name": "40",
        "operation_type": "draw_line",
        "x": 299.5,
        "y": 298.5,
        "color": "#0F0",
        "force": 0.5751953125,
        "editted_by": "kondo"
    },
    {
        "editted_at": 1608628794193,
        "editted_at_": 1608628794188.814,
        "sample_name": "40",
        "operation_type": "draw_line",
        "x": 299,
        "y": 296,
        "color": "#0F0",
        "force": 0.580078125,
        "editted_by": "kondo"
    },
    {
        "editted_at": 1608628794210,
        "editted_at_": 1608628794203.689,
        "sample_name": "40",
        "operation_type": "draw_line",
        "x": 298,
        "y": 293.5,
        "color": "#0F0",
        "force": 0.58203125,
        "editted_by": "kondo"
    },
    {
        "editted_at": 1608628794227,
        "editted_at_": 1608628794219.0488,
        "sample_name": "40",
        "operation_type": "draw_line",
        "x": 297,
        "y": 291,
        "color": "#0F0",
        "force": 0.58203125,
        "editted_by": "kondo"
    },
    {
        "editted_at": 1608628794243,
        "editted_at_": 1608628794241.814,
        "sample_name": "40",
        "operation_type": "draw_line",
        "x": 295,
        "y": 287.5,
        "color": "#0F0",
        "force": 0.59765625,
        "editted_by": "kondo"
    },
    {
        "editted_at": 1608628794260,
        "editted_at_": 1608628794257.249,
        "sample_name": "40",
        "operation_type": "draw_line",
        "x": 294,
        "y": 285.5,
        "color": "#0F0",
        "force": 0.609375,
        "editted_by": "kondo"
    },
    {
        "editted_at": 1608628794277,
        "editted_at_": 1608628794272.0388,
        "sample_name": "40",
        "operation_type": "draw_line",
        "x": 293,
        "y": 283.5,
        "color": "#0F0",
        "force": 0.609375,
        "editted_by": "kondo"
    },
    {
        "editted_at": 1608628794293,
        "editted_at_": 1608628794286.814,
        "sample_name": "40",
        "operation_type": "draw_line",
        "x": 291.5,
        "y": 281.5,
        "color": "#0F0",
        "force": 0.611328125,
        "editted_by": "kondo"
    },
    {
        "editted_at": 1608628794310,
        "editted_at_": 1608628794309.129,
        "sample_name": "40",
        "operation_type": "draw_line",
        "x": 289,
        "y": 278.5,
        "color": "#0F0",
        "force": 0.62109375,
        "editted_by": "kondo"
    },
    {
        "editted_at": 1608628794327,
        "editted_at_": 1608628794323.8289,
        "sample_name": "40",
        "operation_type": "draw_line",
        "x": 287,
        "y": 277.5,
        "color": "#0F0",
        "force": 0.6298828125,
        "editted_by": "kondo"
    },
    {
        "editted_at": 1608628794343,
        "editted_at_": 1608628794339.359,
        "sample_name": "40",
        "operation_type": "draw_line",
        "x": 286,
        "y": 276.5,
        "color": "#0F0",
        "force": 0.634765625,
        "editted_by": "kondo"
    },
    {
        "editted_at": 1608628794360,
        "editted_at_": 1608628794353.7039,
        "sample_name": "40",
        "operation_type": "draw_line",
        "x": 284.5,
        "y": 275,
        "color": "#0F0",
        "force": 0.63671875,
        "editted_by": "kondo"
    },
    {
        "editted_at": 1608628794377,
        "editted_at_": 1608628794369.0989,
        "sample_name": "40",
        "operation_type": "draw_line",
        "x": 283,
        "y": 274,
        "color": "#0F0",
        "force": 0.640625,
        "editted_by": "kondo"
    },
    {
        "editted_at": 1608628794393,
        "editted_at_": 1608628794392.3188,
        "sample_name": "40",
        "operation_type": "draw_line",
        "x": 281.5,
        "y": 272,
        "color": "#0F0",
        "force": 0.65234375,
        "editted_by": "kondo"
    },
    {
        "editted_at": 1608628794410,
        "editted_at_": 1608628794407.4238,
        "sample_name": "40",
        "operation_type": "draw_line",
        "x": 280,
        "y": 271,
        "color": "#0F0",
        "force": 0.6640625,
        "editted_by": "kondo"
    },
    {
        "editted_at": 1608628794427,
        "editted_at_": 1608628794421.999,
        "sample_name": "40",
        "operation_type": "draw_line",
        "x": 278.5,
        "y": 270,
        "color": "#0F0",
        "force": 0.6728515625,
        "editted_by": "kondo"
    },
    {
        "editted_at": 1608628794443,
        "editted_at_": 1608628794436.234,
        "sample_name": "40",
        "operation_type": "draw_line",
        "x": 277.5,
        "y": 269.5,
        "color": "#0F0",
        "force": 0.6708984375,
        "editted_by": "kondo"
    },
    {
        "editted_at": 1608628794460,
        "editted_at_": 1608628794459.004,
        "sample_name": "40",
        "operation_type": "draw_line",
        "x": 276,
        "y": 268,
        "color": "#0F0",
        "force": 0.6708984375,
        "editted_by": "kondo"
    },
    {
        "editted_at": 1608628794477,
        "editted_at_": 1608628794473.824,
        "sample_name": "40",
        "operation_type": "draw_line",
        "x": 274.5,
        "y": 267,
        "color": "#0F0",
        "force": 0.6708984375,
        "editted_by": "kondo"
    },
    {
        "editted_at": 1608628794493,
        "editted_at_": 1608628794489.9438,
        "sample_name": "40",
        "operation_type": "draw_line",
        "x": 272.5,
        "y": 266,
        "color": "#0F0",
        "force": 0.6806640625,
        "editted_by": "kondo"
    },
    {
        "editted_at": 1608628794510,
        "editted_at_": 1608628794503.114,
        "sample_name": "40",
        "operation_type": "draw_line",
        "x": 270.5,
        "y": 265.5,
        "color": "#0F0",
        "force": 0.6884765625,
        "editted_by": "kondo"
    },
    {
        "editted_at": 1608628794527,
        "editted_at_": 1608628794518.629,
        "sample_name": "40",
        "operation_type": "draw_line",
        "x": 268,
        "y": 265,
        "color": "#0F0",
        "force": 0.6923828125,
        "editted_by": "kondo"
    },
    {
        "editted_at": 1608628794543,
        "editted_at_": 1608628794541.804,
        "sample_name": "40",
        "operation_type": "draw_line",
        "x": 265.5,
        "y": 264.5,
        "color": "#0F0",
        "force": 0.6953125,
        "editted_by": "kondo"
    },
    {
        "editted_at": 1608628794560,
        "editted_at_": 1608628794557.469,
        "sample_name": "40",
        "operation_type": "draw_line",
        "x": 263.5,
        "y": 264,
        "color": "#0F0",
        "force": 0.6953125,
        "editted_by": "kondo"
    },
    {
        "editted_at": 1608628794577,
        "editted_at_": 1608628794571.629,
        "sample_name": "40",
        "operation_type": "draw_line",
        "x": 261.5,
        "y": 263.5,
        "color": "#0F0",
        "force": 0.6953125,
        "editted_by": "kondo"
    },
    {
        "editted_at": 1608628794594,
        "editted_at_": 1608628794586.9338,
        "sample_name": "40",
        "operation_type": "draw_line",
        "x": 259.5,
        "y": 262.5,
        "color": "#0F0",
        "force": 0.705078125,
        "editted_by": "kondo"
    },
    {
        "editted_at": 1608628794610,
        "editted_at_": 1608628794609.469,
        "sample_name": "40",
        "operation_type": "draw_line",
        "x": 256.5,
        "y": 261.5,
        "color": "#0F0",
        "force": 0.716796875,
        "editted_by": "kondo"
    },
    {
        "editted_at": 1608628794627,
        "editted_at_": 1608628794623.909,
        "sample_name": "40",
        "operation_type": "draw_line",
        "x": 254.5,
        "y": 260.5,
        "color": "#0F0",
        "force": 0.71875,
        "editted_by": "kondo"
    },
    {
        "editted_at": 1608628794644,
        "editted_at_": 1608628794638.844,
        "sample_name": "40",
        "operation_type": "draw_line",
        "x": 253,
        "y": 260,
        "color": "#0F0",
        "force": 0.71875,
        "editted_by": "kondo"
    },
    {
        "editted_at": 1608628794660,
        "editted_at_": 1608628794652.969,
        "sample_name": "40",
        "operation_type": "draw_line",
        "x": 251,
        "y": 259,
        "color": "#0F0",
        "force": 0.71875,
        "editted_by": "kondo"
    },
    {
        "editted_at": 1608628794677,
        "editted_at_": 1608628794668.114,
        "sample_name": "40",
        "operation_type": "draw_line",
        "x": 249.5,
        "y": 257.5,
        "color": "#0F0",
        "force": 0.71875,
        "editted_by": "kondo"
    },
    {
        "editted_at": 1608628794694,
        "editted_at_": 1608628794692.534,
        "sample_name": "40",
        "operation_type": "draw_line",
        "x": 246.5,
        "y": 256,
        "color": "#0F0",
        "force": 0.71875,
        "editted_by": "kondo"
    },
    {
        "editted_at": 1608628794710,
        "editted_at_": 1608628794707.394,
        "sample_name": "40",
        "operation_type": "draw_line",
        "x": 244.5,
        "y": 254.5,
        "color": "#0F0",
        "force": 0.71875,
        "editted_by": "kondo"
    },
    {
        "editted_at": 1608628794727,
        "editted_at_": 1608628794722.294,
        "sample_name": "40",
        "operation_type": "draw_line",
        "x": 242.5,
        "y": 253,
        "color": "#0F0",
        "force": 0.724609375,
        "editted_by": "kondo"
    },
    {
        "editted_at": 1608628794744,
        "editted_at_": 1608628794736.7888,
        "sample_name": "40",
        "operation_type": "draw_line",
        "x": 240,
        "y": 252.5,
        "color": "#0F0",
        "force": 0.736328125,
        "editted_by": "kondo"
    },
    {
        "editted_at": 1608628794760,
        "editted_at_": 1608628794759.304,
        "sample_name": "40",
        "operation_type": "draw_line",
        "x": 237.5,
        "y": 251.5,
        "color": "#0F0",
        "force": 0.736328125,
        "editted_by": "kondo"
    },
    {
        "editted_at": 1608628794777,
        "editted_at_": 1608628794774.394,
        "sample_name": "40",
        "operation_type": "draw_line",
        "x": 236,
        "y": 250.5,
        "color": "#0F0",
        "force": 0.7275390625,
        "editted_by": "kondo"
    },
    {
        "editted_at": 1608628794794,
        "editted_at_": 1608628794789.9539,
        "sample_name": "40",
        "operation_type": "draw_line",
        "x": 235,
        "y": 249.5,
        "color": "#0F0",
        "force": 0.732421875,
        "editted_by": "kondo"
    },
    {
        "editted_at": 1608628794810,
        "editted_at_": 1608628794804.354,
        "sample_name": "40",
        "operation_type": "draw_line",
        "x": 233,
        "y": 248,
        "color": "#0F0",
        "force": 0.7353515625,
        "editted_by": "kondo"
    },
    {
        "editted_at": 1608628794827,
        "editted_at_": 1608628794818.864,
        "sample_name": "40",
        "operation_type": "draw_line",
        "x": 230.5,
        "y": 246.5,
        "color": "#0F0",
        "force": 0.7294921875,
        "editted_by": "kondo"
    },
    {
        "editted_at": 1608628794844,
        "editted_at_": 1608628794842.009,
        "sample_name": "40",
        "operation_type": "draw_line",
        "x": 226,
        "y": 245.5,
        "color": "#0F0",
        "force": 0.7275390625,
        "editted_by": "kondo"
    },
    {
        "editted_at": 1608628794860,
        "editted_at_": 1608628794857.649,
        "sample_name": "40",
        "operation_type": "draw_line",
        "x": 223.5,
        "y": 245,
        "color": "#0F0",
        "force": 0.7294921875,
        "editted_by": "kondo"
    },
    {
        "editted_at": 1608628794877,
        "editted_at_": 1608628794872.379,
        "sample_name": "40",
        "operation_type": "draw_line",
        "x": 221.5,
        "y": 244,
        "color": "#0F0",
        "force": 0.7294921875,
        "editted_by": "kondo"
    },
    {
        "editted_at": 1608628794894,
        "editted_at_": 1608628794887.4238,
        "sample_name": "40",
        "operation_type": "draw_line",
        "x": 219.5,
        "y": 243.5,
        "color": "#0F0",
        "force": 0.7294921875,
        "editted_by": "kondo"
    },
    {
        "editted_at": 1608628794910,
        "editted_at_": 1608628794908.7039,
        "sample_name": "40",
        "operation_type": "draw_line",
        "x": 216.5,
        "y": 242.5,
        "color": "#0F0",
        "force": 0.736328125,
        "editted_by": "kondo"
    },
    {
        "editted_at": 1608628794927,
        "editted_at_": 1608628794923.8289,
        "sample_name": "40",
        "operation_type": "draw_line",
        "x": 215,
        "y": 243,
        "color": "#0F0",
        "force": 0.736328125,
        "editted_by": "kondo"
    },
    {
        "editted_at": 1608628794944,
        "editted_at_": 1608628794939.749,
        "sample_name": "40",
        "operation_type": "draw_line",
        "x": 213,
        "y": 243,
        "color": "#0F0",
        "force": 0.73046875,
        "editted_by": "kondo"
    },
    {
        "editted_at": 1608628794961,
        "editted_at_": 1608628794954.189,
        "sample_name": "40",
        "operation_type": "draw_line",
        "x": 211,
        "y": 243.5,
        "color": "#0F0",
        "force": 0.7275390625,
        "editted_by": "kondo"
    },
    {
        "editted_at": 1608628794977,
        "editted_at_": 1608628794969.3489,
        "sample_name": "40",
        "operation_type": "draw_line",
        "x": 209.5,
        "y": 243.5,
        "color": "#0F0",
        "force": 0.7275390625,
        "editted_by": "kondo"
    },
    {
        "editted_at": 1608628794994,
        "editted_at_": 1608628794993.159,
        "sample_name": "40",
        "operation_type": "draw_line",
        "x": 207,
        "y": 244,
        "color": "#0F0",
        "force": 0.7275390625,
        "editted_by": "kondo"
    },
    {
        "editted_at": 1608628795010,
        "editted_at_": 1608628795007.7239,
        "sample_name": "40",
        "operation_type": "draw_line",
        "x": 205,
        "y": 244.5,
        "color": "#0F0",
        "force": 0.7275390625,
        "editted_by": "kondo"
    },
    {
        "editted_at": 1608628795027,
        "editted_at_": 1608628795022.639,
        "sample_name": "40",
        "operation_type": "draw_line",
        "x": 203.5,
        "y": 244.5,
        "color": "#0F0",
        "force": 0.7275390625,
        "editted_by": "kondo"
    },
    {
        "editted_at": 1608628795044,
        "editted_at_": 1608628795037.3088,
        "sample_name": "40",
        "operation_type": "draw_line",
        "x": 202,
        "y": 245,
        "color": "#0F0",
        "force": 0.7275390625,
        "editted_by": "kondo"
    },
    {
        "editted_at": 1608628795060,
        "editted_at_": 1608628795059.284,
        "sample_name": "40",
        "operation_type": "draw_line",
        "x": 200,
        "y": 245.5,
        "color": "#0F0",
        "force": 0.7275390625,
        "editted_by": "kondo"
    },
    {
        "editted_at": 1608628795077,
        "editted_at_": 1608628795074.124,
        "sample_name": "40",
        "operation_type": "draw_line",
        "x": 199,
        "y": 245,
        "color": "#0F0",
        "force": 0.7275390625,
        "editted_by": "kondo"
    },
    {
        "editted_at": 1608628795094,
        "editted_at_": 1608628795089.524,
        "sample_name": "40",
        "operation_type": "draw_line",
        "x": 197.5,
        "y": 245,
        "color": "#0F0",
        "force": 0.7333984375,
        "editted_by": "kondo"
    },
    {
        "editted_at": 1608628795111,
        "editted_at_": 1608628795104.369,
        "sample_name": "40",
        "operation_type": "draw_line",
        "x": 196.5,
        "y": 244.5,
        "color": "#0F0",
        "force": 0.736328125,
        "editted_by": "kondo"
    },
    {
        "editted_at": 1608628795127,
        "editted_at_": 1608628795119.8489,
        "sample_name": "40",
        "operation_type": "draw_line",
        "x": 194.5,
        "y": 244.5,
        "color": "#0F0",
        "force": 0.7353515625,
        "editted_by": "kondo"
    },
    {
        "editted_at": 1608628795144,
        "editted_at_": 1608628795143.024,
        "sample_name": "40",
        "operation_type": "draw_line",
        "x": 192.5,
        "y": 245.5,
        "color": "#0F0",
        "force": 0.7353515625,
        "editted_by": "kondo"
    },
    {
        "editted_at": 1608628795161,
        "editted_at_": 1608628795157.784,
        "sample_name": "40",
        "operation_type": "draw_line",
        "x": 191,
        "y": 245.5,
        "color": "#0F0",
        "force": 0.7294921875,
        "editted_by": "kondo"
    },
    {
        "editted_at": 1608628795177,
        "editted_at_": 1608628795172.5889,
        "sample_name": "40",
        "operation_type": "draw_line",
        "x": 190,
        "y": 246,
        "color": "#0F0",
        "force": 0.7275390625,
        "editted_by": "kondo"
    },
    {
        "editted_at": 1608628795194,
        "editted_at_": 1608628795187.2039,
        "sample_name": "40",
        "operation_type": "draw_line",
        "x": 189,
        "y": 246,
        "color": "#0F0",
        "force": 0.7275390625,
        "editted_by": "kondo"
    },
    {
        "editted_at": 1608628795210,
        "editted_at_": 1608628795209.984,
        "sample_name": "40",
        "operation_type": "draw_line",
        "x": 187,
        "y": 246,
        "color": "#0F0",
        "force": 0.7275390625,
        "editted_by": "kondo"
    },
    {
        "editted_at": 1608628795227,
        "editted_at_": 1608628795224.074,
        "sample_name": "40",
        "operation_type": "draw_line",
        "x": 186,
        "y": 246.5,
        "color": "#0F0",
        "force": 0.7275390625,
        "editted_by": "kondo"
    },
    {
        "editted_at": 1608628795244,
        "editted_at_": 1608628795239.899,
        "sample_name": "40",
        "operation_type": "draw_line",
        "x": 184.5,
        "y": 248,
        "color": "#0F0",
        "force": 0.7275390625,
        "editted_by": "kondo"
    },
    {
        "editted_at": 1608628795261,
        "editted_at_": 1608628795254.854,
        "sample_name": "40",
        "operation_type": "draw_line",
        "x": 184,
        "y": 250,
        "color": "#0F0",
        "force": 0.724609375,
        "editted_by": "kondo"
    },
    {
        "editted_at": 1608628795277,
        "editted_at_": 1608628795269.314,
        "sample_name": "40",
        "operation_type": "draw_line",
        "x": 184,
        "y": 251,
        "color": "#0F0",
        "force": 0.72265625,
        "editted_by": "kondo"
    },
    {
        "editted_at": 1608628795294,
        "editted_at_": 1608628795292.509,
        "sample_name": "40",
        "operation_type": "draw_line",
        "x": 184,
        "y": 253.5,
        "color": "#0F0",
        "force": 0.720703125,
        "editted_by": "kondo"
    },
    {
        "editted_at": 1608628795311,
        "editted_at_": 1608628795307.764,
        "sample_name": "40",
        "operation_type": "draw_line",
        "x": 184,
        "y": 255.5,
        "color": "#0F0",
        "force": 0.720703125,
        "editted_by": "kondo"
    },
    {
        "editted_at": 1608628795327,
        "editted_at_": 1608628795323.284,
        "sample_name": "40",
        "operation_type": "draw_line",
        "x": 184.5,
        "y": 257,
        "color": "#0F0",
        "force": 0.720703125,
        "editted_by": "kondo"
    },
    {
        "editted_at": 1608628795344,
        "editted_at_": 1608628795338.064,
        "sample_name": "40",
        "operation_type": "draw_line",
        "x": 185,
        "y": 259,
        "color": "#0F0",
        "force": 0.71875,
        "editted_by": "kondo"
    },
    {
        "editted_at": 1608628795361,
        "editted_at_": 1608628795359.814,
        "sample_name": "40",
        "operation_type": "draw_line",
        "x": 186,
        "y": 262.5,
        "color": "#0F0",
        "force": 0.71875,
        "editted_by": "kondo"
    },
    {
        "editted_at": 1608628795377,
        "editted_at_": 1608628795374.2888,
        "sample_name": "40",
        "operation_type": "draw_line",
        "x": 186.5,
        "y": 265.5,
        "color": "#0F0",
        "force": 0.71875,
        "editted_by": "kondo"
    },
    {
        "editted_at": 1608628795394,
        "editted_at_": 1608628795390.169,
        "sample_name": "40",
        "operation_type": "draw_line",
        "x": 186.5,
        "y": 268.5,
        "color": "#0F0",
        "force": 0.71875,
        "editted_by": "kondo"
    },
    {
        "editted_at": 1608628795411,
        "editted_at_": 1608628795404.844,
        "sample_name": "40",
        "operation_type": "draw_line",
        "x": 186.5,
        "y": 271,
        "color": "#0F0",
        "force": 0.71875,
        "editted_by": "kondo"
    },
    {
        "editted_at": 1608628795427,
        "editted_at_": 1608628795419.8188,
        "sample_name": "40",
        "operation_type": "draw_line",
        "x": 186.5,
        "y": 273,
        "color": "#0F0",
        "force": 0.71875,
        "editted_by": "kondo"
    },
    {
        "editted_at": 1608628795444,
        "editted_at_": 1608628795443.0488,
        "sample_name": "40",
        "operation_type": "draw_line",
        "x": 187,
        "y": 276.5,
        "color": "#0F0",
        "force": 0.71875,
        "editted_by": "kondo"
    },
    {
        "editted_at": 1608628795461,
        "editted_at_": 1608628795457.994,
        "sample_name": "40",
        "operation_type": "draw_line",
        "x": 187.5,
        "y": 279.5,
        "color": "#0F0",
        "force": 0.71875,
        "editted_by": "kondo"
    },
    {
        "editted_at": 1608628795477,
        "editted_at_": 1608628795473.1638,
        "sample_name": "40",
        "operation_type": "draw_line",
        "x": 188,
        "y": 283,
        "color": "#0F0",
        "force": 0.716796875,
        "editted_by": "kondo"
    },
    {
        "editted_at": 1608628795494,
        "editted_at_": 1608628795487.629,
        "sample_name": "40",
        "operation_type": "draw_line",
        "x": 188.5,
        "y": 286.5,
        "color": "#0F0",
        "force": 0.716796875,
        "editted_by": "kondo"
    },
    {
        "editted_at": 1608628795511,
        "editted_at_": 1608628795510.274,
        "sample_name": "40",
        "operation_type": "draw_line",
        "x": 189,
        "y": 291,
        "color": "#0F0",
        "force": 0.716796875,
        "editted_by": "kondo"
    },
    {
        "editted_at": 1608628795528,
        "editted_at_": 1608628795525.2788,
        "sample_name": "40",
        "operation_type": "draw_line",
        "x": 189.5,
        "y": 294.5,
        "color": "#0F0",
        "force": 0.716796875,
        "editted_by": "kondo"
    },
    {
        "editted_at": 1608628795544,
        "editted_at_": 1608628795539.5488,
        "sample_name": "40",
        "operation_type": "draw_line",
        "x": 190,
        "y": 297.5,
        "color": "#0F0",
        "force": 0.716796875,
        "editted_by": "kondo"
    },
    {
        "editted_at": 1608628795561,
        "editted_at_": 1608628795554.874,
        "sample_name": "40",
        "operation_type": "draw_line",
        "x": 191,
        "y": 301.5,
        "color": "#0F0",
        "force": 0.716796875,
        "editted_by": "kondo"
    },
    {
        "editted_at": 1608628795578,
        "editted_at_": 1608628795569.889,
        "sample_name": "40",
        "operation_type": "draw_line",
        "x": 192,
        "y": 304.5,
        "color": "#0F0",
        "force": 0.71484375,
        "editted_by": "kondo"
    },
    {
        "editted_at": 1608628795594,
        "editted_at_": 1608628795592.9539,
        "sample_name": "40",
        "operation_type": "draw_line",
        "x": 193.5,
        "y": 309,
        "color": "#0F0",
        "force": 0.71484375,
        "editted_by": "kondo"
    },
    {
        "editted_at": 1608628795611,
        "editted_at_": 1608628795608.094,
        "sample_name": "40",
        "operation_type": "draw_line",
        "x": 195,
        "y": 312,
        "color": "#0F0",
        "force": 0.71484375,
        "editted_by": "kondo"
    },
    {
        "editted_at": 1608628795628,
        "editted_at_": 1608628795623.499,
        "sample_name": "40",
        "operation_type": "draw_line",
        "x": 196.5,
        "y": 315.5,
        "color": "#0F0",
        "force": 0.716796875,
        "editted_by": "kondo"
    },
    {
        "editted_at": 1608628795644,
        "editted_at_": 1608628795637.969,
        "sample_name": "40",
        "operation_type": "draw_line",
        "x": 197.5,
        "y": 318.5,
        "color": "#0F0",
        "force": 0.7060546875,
        "editted_by": "kondo"
    },
    {
        "editted_at": 1608628795661,
        "editted_at_": 1608628795659.8088,
        "sample_name": "40",
        "operation_type": "draw_line",
        "x": 199,
        "y": 322,
        "color": "#0F0",
        "force": 0.712890625,
        "editted_by": "kondo"
    },
    {
        "editted_at": 1608628795678,
        "editted_at_": 1608628795675.369,
        "sample_name": "40",
        "operation_type": "draw_line",
        "x": 200.5,
        "y": 324,
        "color": "#0F0",
        "force": 0.712890625,
        "editted_by": "kondo"
    },
    {
        "editted_at": 1608628795694,
        "editted_at_": 1608628795690.4038,
        "sample_name": "40",
        "operation_type": "draw_line",
        "x": 202.5,
        "y": 325,
        "color": "#0F0",
        "force": 0.712890625,
        "editted_by": "kondo"
    },
    {
        "editted_at": 1608628795711,
        "editted_at_": 1608628795704.459,
        "sample_name": "40",
        "operation_type": "draw_line",
        "x": 204.5,
        "y": 326.5,
        "color": "#0F0",
        "force": 0.712890625,
        "editted_by": "kondo"
    },
    {
        "editted_at": 1608628795727,
        "editted_at_": 1608628795719.484,
        "sample_name": "40",
        "operation_type": "draw_line",
        "x": 206.5,
        "y": 328.5,
        "color": "#0F0",
        "force": 0.712890625,
        "editted_by": "kondo"
    },
    {
        "editted_at": 1608628795744,
        "editted_at_": 1608628795743.609,
        "sample_name": "40",
        "operation_type": "draw_line",
        "x": 209,
        "y": 331.5,
        "color": "#0F0",
        "force": 0.712890625,
        "editted_by": "kondo"
    },
    {
        "editted_at": 1608628795761,
        "editted_at_": 1608628795758.609,
        "sample_name": "40",
        "operation_type": "draw_line",
        "x": 211.5,
        "y": 333,
        "color": "#0F0",
        "force": 0.712890625,
        "editted_by": "kondo"
    },
    {
        "editted_at": 1608628795778,
        "editted_at_": 1608628795773.139,
        "sample_name": "40",
        "operation_type": "draw_line",
        "x": 213.5,
        "y": 334.5,
        "color": "#0F0",
        "force": 0.712890625,
        "editted_by": "kondo"
    },
    {
        "editted_at": 1608628795794,
        "editted_at_": 1608628795788.419,
        "sample_name": "40",
        "operation_type": "draw_line",
        "x": 215.5,
        "y": 336,
        "color": "#0F0",
        "force": 0.712890625,
        "editted_by": "kondo"
    },
    {
        "editted_at": 1608628795811,
        "editted_at_": 1608628795810.129,
        "sample_name": "40",
        "operation_type": "draw_line",
        "x": 218.5,
        "y": 338.5,
        "color": "#0F0",
        "force": 0.705078125,
        "editted_by": "kondo"
    },
    {
        "editted_at": 1608628795828,
        "editted_at_": 1608628795825.034,
        "sample_name": "40",
        "operation_type": "draw_line",
        "x": 220,
        "y": 340.5,
        "color": "#0F0",
        "force": 0.7109375,
        "editted_by": "kondo"
    },
    {
        "editted_at": 1608628795844,
        "editted_at_": 1608628795840.129,
        "sample_name": "40",
        "operation_type": "draw_line",
        "x": 222,
        "y": 342.5,
        "color": "#0F0",
        "force": 0.712890625,
        "editted_by": "kondo"
    },
    {
        "editted_at": 1608628795861,
        "editted_at_": 1608628795854.6638,
        "sample_name": "40",
        "operation_type": "draw_line",
        "x": 224,
        "y": 345,
        "color": "#0F0",
        "force": 0.712890625,
        "editted_by": "kondo"
    },
    {
        "editted_at": 1608628795878,
        "editted_at_": 1608628795869.739,
        "sample_name": "40",
        "operation_type": "draw_line",
        "x": 226,
        "y": 346.5,
        "color": "#0F0",
        "force": 0.712890625,
        "editted_by": "kondo"
    },
    {
        "editted_at": 1608628795894,
        "editted_at_": 1608628795893.8188,
        "sample_name": "40",
        "operation_type": "draw_line",
        "x": 229,
        "y": 349,
        "color": "#0F0",
        "force": 0.712890625,
        "editted_by": "kondo"
    },
    {
        "editted_at": 1608628795911,
        "editted_at_": 1608628795908.489,
        "sample_name": "40",
        "operation_type": "draw_line",
        "x": 231,
        "y": 350.5,
        "color": "#0F0",
        "force": 0.712890625,
        "editted_by": "kondo"
    },
    {
        "editted_at": 1608628795928,
        "editted_at_": 1608628795923.619,
        "sample_name": "40",
        "operation_type": "draw_line",
        "x": 233,
        "y": 352.5,
        "color": "#0F0",
        "force": 0.712890625,
        "editted_by": "kondo"
    },
    {
        "editted_at": 1608628795944,
        "editted_at_": 1608628795938.484,
        "sample_name": "40",
        "operation_type": "draw_line",
        "x": 234.5,
        "y": 355,
        "color": "#0F0",
        "force": 0.712890625,
        "editted_by": "kondo"
    },
    {
        "editted_at": 1608628795961,
        "editted_at_": 1608628795960.159,
        "sample_name": "40",
        "operation_type": "draw_line",
        "x": 238,
        "y": 358.5,
        "color": "#0F0",
        "force": 0.712890625,
        "editted_by": "kondo"
    },
    {
        "editted_at": 1608628795978,
        "editted_at_": 1608628795975.3489,
        "sample_name": "40",
        "operation_type": "draw_line",
        "x": 240.5,
        "y": 360,
        "color": "#0F0",
        "force": 0.70703125,
        "editted_by": "kondo"
    },
    {
        "editted_at": 1608628795994,
        "editted_at_": 1608628795990.739,
        "sample_name": "40",
        "operation_type": "draw_line",
        "x": 243,
        "y": 361.5,
        "color": "#0F0",
        "force": 0.7099609375,
        "editted_by": "kondo"
    },
    {
        "editted_at": 1608628796011,
        "editted_at_": 1608628796005.129,
        "sample_name": "40",
        "operation_type": "draw_line",
        "x": 245.5,
        "y": 363,
        "color": "#0F0",
        "force": 0.7119140625,
        "editted_by": "kondo"
    },
    {
        "editted_at": 1608628796028,
        "editted_at_": 1608628796020.2039,
        "sample_name": "40",
        "operation_type": "draw_line",
        "x": 248,
        "y": 364.5,
        "color": "#0F0",
        "force": 0.7119140625,
        "editted_by": "kondo"
    },
    {
        "editted_at": 1608628796044,
        "editted_at_": 1608628796043.774,
        "sample_name": "40",
        "operation_type": "draw_line",
        "x": 251.5,
        "y": 367.5,
        "color": "#0F0",
        "force": 0.7119140625,
        "editted_by": "kondo"
    },
    {
        "editted_at": 1608628796061,
        "editted_at_": 1608628796058.804,
        "sample_name": "40",
        "operation_type": "draw_line",
        "x": 254,
        "y": 369.5,
        "color": "#0F0",
        "force": 0.7119140625,
        "editted_by": "kondo"
    },
    {
        "editted_at": 1608628796078,
        "editted_at_": 1608628796073.374,
        "sample_name": "40",
        "operation_type": "draw_line",
        "x": 256.5,
        "y": 371,
        "color": "#0F0",
        "force": 0.7119140625,
        "editted_by": "kondo"
    },
    {
        "editted_at": 1608628796095,
        "editted_at_": 1608628796088.509,
        "sample_name": "40",
        "operation_type": "draw_line",
        "x": 259,
        "y": 372,
        "color": "#0F0",
        "force": 0.7119140625,
        "editted_by": "kondo"
    },
    {
        "editted_at": 1608628796111,
        "editted_at_": 1608628796110.149,
        "sample_name": "40",
        "operation_type": "draw_line",
        "x": 261.5,
        "y": 372.5,
        "color": "#0F0",
        "force": 0.7138671875,
        "editted_by": "kondo"
    },
    {
        "editted_at": 1608628796128,
        "editted_at_": 1608628796125.604,
        "sample_name": "40",
        "operation_type": "draw_line",
        "x": 263,
        "y": 373,
        "color": "#0F0",
        "force": 0.7158203125,
        "editted_by": "kondo"
    },
    {
        "editted_at": 1608628796145,
        "editted_at_": 1608628796140.129,
        "sample_name": "40",
        "operation_type": "draw_line",
        "x": 264.5,
        "y": 374,
        "color": "#0F0",
        "force": 0.7158203125,
        "editted_by": "kondo"
    },
    {
        "editted_at": 1608628796161,
        "editted_at_": 1608628796155.3489,
        "sample_name": "40",
        "operation_type": "draw_line",
        "x": 266.5,
        "y": 375,
        "color": "#0F0",
        "force": 0.7158203125,
        "editted_by": "kondo"
    },
    {
        "editted_at": 1608628796178,
        "editted_at_": 1608628796170.5388,
        "sample_name": "40",
        "operation_type": "draw_line",
        "x": 269,
        "y": 375.5,
        "color": "#0F0",
        "force": 0.7158203125,
        "editted_by": "kondo"
    },
    {
        "editted_at": 1608628796194,
        "editted_at_": 1608628796193.114,
        "sample_name": "40",
        "operation_type": "draw_line",
        "x": 273,
        "y": 375.5,
        "color": "#0F0",
        "force": 0.7158203125,
        "editted_by": "kondo"
    },
    {
        "editted_at": 1608628796211,
        "editted_at_": 1608628796209.0288,
        "sample_name": "40",
        "operation_type": "draw_line",
        "x": 275,
        "y": 375,
        "color": "#0F0",
        "force": 0.7158203125,
        "editted_by": "kondo"
    },
    {
        "editted_at": 1608628796228,
        "editted_at_": 1608628796224.004,
        "sample_name": "40",
        "operation_type": "draw_line",
        "x": 277,
        "y": 375.5,
        "color": "#0F0",
        "force": 0.7158203125,
        "editted_by": "kondo"
    },
    {
        "editted_at": 1608628796245,
        "editted_at_": 1608628796238.584,
        "sample_name": "40",
        "operation_type": "draw_line",
        "x": 278.5,
        "y": 376,
        "color": "#0F0",
        "force": 0.7177734375,
        "editted_by": "kondo"
    },
    {
        "editted_at": 1608628796261,
        "editted_at_": 1608628796260.114,
        "sample_name": "40",
        "operation_type": "draw_line",
        "x": 281,
        "y": 376.5,
        "color": "#0F0",
        "force": 0.7177734375,
        "editted_by": "kondo"
    },
    {
        "editted_at": 1608628796278,
        "editted_at_": 1608628796275.5688,
        "sample_name": "40",
        "operation_type": "draw_line",
        "x": 283.5,
        "y": 376,
        "color": "#0F0",
        "force": 0.7177734375,
        "editted_by": "kondo"
    },
    {
        "editted_at": 1608628796297,
        "editted_at_": 1608628796289.9338,
        "sample_name": "40",
        "operation_type": "draw_line",
        "x": 286,
        "y": 375.5,
        "color": "#0F0",
        "force": 0.7197265625,
        "editted_by": "kondo"
    },
    {
        "editted_at": 1608628796311,
        "editted_at_": 1608628796305.064,
        "sample_name": "40",
        "operation_type": "draw_line",
        "x": 287.5,
        "y": 375,
        "color": "#0F0",
        "force": 0.7197265625,
        "editted_by": "kondo"
    },
    {
        "editted_at": 1608628796328,
        "editted_at_": 1608628796320.574,
        "sample_name": "40",
        "operation_type": "draw_line",
        "x": 289.5,
        "y": 374.5,
        "color": "#0F0",
        "force": 0.7197265625,
        "editted_by": "kondo"
    },
    {
        "editted_at": 1608628796344,
        "editted_at_": 1608628796343.564,
        "sample_name": "40",
        "operation_type": "draw_line",
        "x": 291.5,
        "y": 374,
        "color": "#0F0",
        "force": 0.7216796875,
        "editted_by": "kondo"
    },
    {
        "editted_at": 1608628796362,
        "editted_at_": 1608628796358.4739,
        "sample_name": "40",
        "operation_type": "draw_line",
        "x": 293,
        "y": 373,
        "color": "#0F0",
        "force": 0.7216796875,
        "editted_by": "kondo"
    },
    {
        "editted_at": 1608628796378,
        "editted_at_": 1608628796373.459,
        "sample_name": "40",
        "operation_type": "draw_line",
        "x": 294.5,
        "y": 372.5,
        "color": "#0F0",
        "force": 0.7216796875,
        "editted_by": "kondo"
    },
    {
        "editted_at": 1608628796395,
        "editted_at_": 1608628796388.7988,
        "sample_name": "40",
        "operation_type": "draw_line",
        "x": 296,
        "y": 371,
        "color": "#0F0",
        "force": 0.7216796875,
        "editted_by": "kondo"
    },
    {
        "editted_at": 1608628796411,
        "editted_at_": 1608628796411.024,
        "sample_name": "40",
        "operation_type": "draw_line",
        "x": 297.5,
        "y": 368.5,
        "color": "#0F0",
        "force": 0.7236328125,
        "editted_by": "kondo"
    },
    {
        "editted_at": 1608628796428,
        "editted_at_": 1608628796425.629,
        "sample_name": "40",
        "operation_type": "draw_line",
        "x": 298.5,
        "y": 367,
        "color": "#0F0",
        "force": 0.7255859375,
        "editted_by": "kondo"
    },
    {
        "editted_at": 1608628796445,
        "editted_at_": 1608628796440.1738,
        "sample_name": "40",
        "operation_type": "draw_line",
        "x": 299,
        "y": 365.5,
        "color": "#0F0",
        "force": 0.7255859375,
        "editted_by": "kondo"
    },
    {
        "editted_at": 1608628796463,
        "editted_at_": 1608628796455.354,
        "sample_name": "40",
        "operation_type": "draw_line",
        "x": 299.5,
        "y": 364,
        "color": "#0F0",
        "force": 0.7255859375,
        "editted_by": "kondo"
    },
    {
        "editted_at": 1608628796478,
        "editted_at_": 1608628796470.4739,
        "sample_name": "40",
        "operation_type": "draw_line",
        "x": 300.5,
        "y": 362.5,
        "color": "#0F0",
        "force": 0.7255859375,
        "editted_by": "kondo"
    },
    {
        "editted_at": 1608628796495,
        "editted_at_": 1608628796494.244,
        "sample_name": "40",
        "operation_type": "draw_line",
        "x": 302,
        "y": 360.5,
        "color": "#0F0",
        "force": 0.7255859375,
        "editted_by": "kondo"
    },
    {
        "editted_at": 1608628796512,
        "editted_at_": 1608628796508.844,
        "sample_name": "40",
        "operation_type": "draw_line",
        "x": 304,
        "y": 358.5,
        "color": "#0F0",
        "force": 0.7275390625,
        "editted_by": "kondo"
    },
    {
        "editted_at": 1608628796528,
        "editted_at_": 1608628796523.919,
        "sample_name": "40",
        "operation_type": "draw_line",
        "x": 305.5,
        "y": 356.5,
        "color": "#0F0",
        "force": 0.734375,
        "editted_by": "kondo"
    },
    {
        "editted_at": 1608628796545,
        "editted_at_": 1608628796538.689,
        "sample_name": "40",
        "operation_type": "draw_line",
        "x": 307,
        "y": 355,
        "color": "#0F0",
        "force": 0.7275390625,
        "editted_by": "kondo"
    },
    {
        "editted_at": 1608628796561,
        "editted_at_": 1608628796560.749,
        "sample_name": "40",
        "operation_type": "draw_line",
        "x": 308,
        "y": 352,
        "color": "#0F0",
        "force": 0.7275390625,
        "editted_by": "kondo"
    },
    {
        "editted_at": 1608628796578,
        "editted_at_": 1608628796575.374,
        "sample_name": "40",
        "operation_type": "draw_line",
        "x": 308.5,
        "y": 351,
        "color": "#0F0",
        "force": 0.7275390625,
        "editted_by": "kondo"
    },
    {
        "editted_at": 1608628796595,
        "editted_at_": 1608628796590.629,
        "sample_name": "40",
        "operation_type": "draw_line",
        "x": 309,
        "y": 349,
        "color": "#0F0",
        "force": 0.7275390625,
        "editted_by": "kondo"
    },
    {
        "editted_at": 1608628796612,
        "editted_at_": 1608628796605.629,
        "sample_name": "40",
        "operation_type": "draw_line",
        "x": 309,
        "y": 347,
        "color": "#0F0",
        "force": 0.7294921875,
        "editted_by": "kondo"
    },
    {
        "editted_at": 1608628796628,
        "editted_at_": 1608628796620.679,
        "sample_name": "40",
        "operation_type": "draw_line",
        "x": 309,
        "y": 343.5,
        "color": "#0F0",
        "force": 0.7294921875,
        "editted_by": "kondo"
    },
    {
        "editted_at": 1608628796645,
        "editted_at_": 1608628796644.119,
        "sample_name": "40",
        "operation_type": "draw_line",
        "x": 308.5,
        "y": 338,
        "color": "#0F0",
        "force": 0.7294921875,
        "editted_by": "kondo"
    },
    {
        "editted_at": 1608628796662,
        "editted_at_": 1608628796650.7788,
        "sample_name": "40",
        "operation_type": "draw_line",
        "x": 307,
        "y": 333,
        "color": "#0F0",
        "force": 0.7197265625,
        "editted_by": "kondo"
    },
    {
        "editted_at": 1608628796668,
        "editted_at_": 1608628796667.2039,
        "sample_name": "40",
        "operation_type": "draw_line",
        "x": 305.5,
        "y": 329,
        "color": "#0F0",
        "force": 0.296875,
        "editted_by": "kondo"
    },
    {
        "editted_at": 1608628796670,
        "editted_at_": 1608628796667.814,
        "sample_name": "40",
        "operation_type": "end_drawing",
        "x": null,
        "y": null,
        "color": null,
        "force": null,
        "editted_by": "kondo"
    },
    {
        "editted_at": 1608628797097,
        "editted_at_": 1608628797093.0688,
        "sample_name": "40",
        "operation_type": "save",
        "x": null,
        "y": null,
        "color": null,
        "force": null,
        "editted_by": "kondo"
    }
]